unit_saas/__init__.py
unit_saas/loader.py
unit_saas/prebuilt.py
unit_saas-0.7.0.dist-info/METADATA
unit_saas-0.7.0.dist-info/WHEEL
unit_saas-0.7.0.dist-info/top_level.txt
unit_saas-0.7.0.dist-info/RECORD
