Metadata-Version: 2.4
Name: unit_saas
Version: 0.7.0
Summary: My SAAS internal package
Author-email: Sanidhya <sanidhyaagrawal2002@gmail.com>
License-Expression: MIT
Requires-Python: >=3.8
Requires-Dist: pandas
Requires-Dist: boto3
Requires-Dist: sqlalchemy
Requires-Dist: numpy
Requires-Dist: matplotlib
Requires-Dist: requests
